opensensemap_api/__init__.py
opensensemap_api/exceptions.py
opensensemap_api-0.2.0.dist-info/LICENSE
opensensemap_api-0.2.0.dist-info/METADATA
opensensemap_api-0.2.0.dist-info/WHEEL
opensensemap_api-0.2.0.dist-info/top_level.txt
opensensemap_api-0.2.0.dist-info/zip-safe
opensensemap_api-0.2.0.dist-info/RECORD
